[{"id": "Julia Roberts", "email_addr": "Julia Roberts <julia@hiresmartvirtualemployees.com>", "name": "Julia Roberts", "report_submitted": false}, {"id": "Angel Cajalne", "email_addr": "Angel Cajalne <Angel@hiresmartvirtualemployees.com>", "name": "Angel Cajalne", "report_submitted": false}, {"id": "Shannen Jaucian", "email_addr": "Shannen Jaucian <Shannen@hiresmartvirtualemployees.com>", "name": "Shannen Jaucian", "report_submitted": false}, {"id": "Pamela Cruz", "email_addr": "Pamela Cruz <Pamela@hiresmartvirtualemployees.com>", "name": "Pamela Cruz", "report_submitted": false}, {"id": "Hannah Alerta", "email_addr": "Hannah Alerta <Hannah@hiresmartvirtualemployees.com>", "name": "Hannah Alerta", "report_submitted": false}, {"id": "Alex Plant", "email_addr": "Alex Plant <Alex@hiresmartvirtualemployees.com>", "name": "Alex Plant", "report_submitted": false}]